CHANGES.rst
LICENSE
grafana_pandas_datasource/__init__.py
grafana_pandas_datasource/config.py
grafana_pandas_datasource/core.py
grafana_pandas_datasource/logging.py
grafana_pandas_datasource/registry.py
grafana_pandas_datasource/service.py
grafana_pandas_datasource-0.3.0.dist-info/LICENSE
grafana_pandas_datasource-0.3.0.dist-info/WHEEL
grafana_pandas_datasource-0.3.0.dist-info/METADATA
grafana_pandas_datasource-0.3.0.dist-info/RECORD
