Metadata-Version: 2.1
Name: grafana-pandas-datasource
Version: 0.3.0
Summary: Serve NumPy data via pandas data frames to Grafana
Home-page: https://community.panodata.org/t/grafana-python-datasource-using-pandas-for-timeseries-and-table-data/148
License: AGPL-3.0
Keywords: grafana,pandas,datasource,grafana-plugin,grafana-datasource,pandas-dataframe
Author: Andreas Motl
Author-email: andreas.motl@panodata.org
Requires-Python: >=3.7.1,<4.0.0
Classifier: Development Status :: 4 - Beta
Classifier: Environment :: Console
Classifier: Intended Audience :: Developers
Classifier: Intended Audience :: Education
Classifier: Intended Audience :: Information Technology
Classifier: Intended Audience :: Science/Research
Classifier: Intended Audience :: System Administrators
Classifier: License :: OSI Approved :: GNU Affero General Public License v3
Classifier: Operating System :: MacOS
Classifier: Operating System :: POSIX
Classifier: Operating System :: Unix
Classifier: Programming Language :: Python
Classifier: Programming Language :: Python :: 3
Classifier: Programming Language :: Python :: 3.10
Classifier: Programming Language :: Python :: 3.7
Classifier: Programming Language :: Python :: 3.8
Classifier: Programming Language :: Python :: 3.9
Classifier: Topic :: Communications
Classifier: Topic :: Database
Classifier: Topic :: Internet
Classifier: Topic :: Internet :: WWW/HTTP :: Indexing/Search
Classifier: Topic :: Scientific/Engineering :: Atmospheric Science
Classifier: Topic :: Scientific/Engineering :: GIS
Classifier: Topic :: Scientific/Engineering :: Human Machine Interfaces
Classifier: Topic :: Scientific/Engineering :: Information Analysis
Classifier: Topic :: Scientific/Engineering :: Interface Engine/Protocol Translator
Classifier: Topic :: Scientific/Engineering :: Visualization
Classifier: Topic :: Software Development :: Libraries
Classifier: Topic :: System :: Archiving
Classifier: Topic :: Text Processing
Classifier: Topic :: Utilities
Requires-Dist: flask (>=1.1.4,<2.0.0)
Requires-Dist: flask-cors (>=3.0.10,<4.0.0)
Requires-Dist: pandas (>=1.3,<2.0)
Project-URL: Issues, https://github.com/panodata/grafana-pandas-datasource/issues
Project-URL: Repository, https://github.com/panodata/grafana-pandas-datasource
